[
  {
    "sprite": "Effects/Bullets/enemybulletB",
    "generateColliders": true,
    "collisionSprite": "Effects/Bullets/enemybulletB_collision",
    "matEmissionPower": 2,
    "matDayCycleMultiplier": 0.0,
    "rows": 4,
    "columns": 5,
    "updateCounter": 2
  },




  {
    "sprite": "Sprites/Enemies/bomber",
    "generateColliders": true,
    "matDayCycleMultiplier": 0.5,
    "rows": 1,
    "columns": 4
  },
  {
    "sprite": "Effects/Bullets/bullet bomb",
    "generateColliders": true,
    "matReflectionPass": false,
    "matEmissionPower": 2
  },
  {
      "sprite": "Effects/Bullets/directional lightning",
      "collisionSpriteScale": "Effects/Bullets/directional lightning_collision",
      "matDayCycleMultiplier": 0,
      "generateColliders": true,
      "matReflectionPass": false,
      "matEmissionPower": 2,
      "rows": 10,
      "columns": 1
  },
  {
    "sprite": "Sprites/Enemies/jumper",
    "generateColliders": true,
    "matDayCycleMultiplier": 0.5,
    "rows": 2,
    "columns": 4
  }
]
